setup.py
src/__init__.py
src/getTFOutput.py
src/tfcloud.py
tf_cloud_api.egg-info/PKG-INFO
tf_cloud_api.egg-info/SOURCES.txt
tf_cloud_api.egg-info/dependency_links.txt
tf_cloud_api.egg-info/entry_points.txt
tf_cloud_api.egg-info/not-zip-safe
tf_cloud_api.egg-info/requires.txt
tf_cloud_api.egg-info/top_level.txt