Metadata-Version: 1.0
Name: tf-cloud-api
Version: 0.0.1
Summary: Script for interact with the tf cloud api
Home-page: https://github.com/redaptiveinc/tf-cloud-api
Author: Mariano Gimenez
Author-email: mariano.gimenez@redaptiveinc.com
License: unlicense
Platform: UNKNOWN
